petite/__init__.py
petite/__main__.py
petite/utils/__init__.py
petite/utils/confirmations.py
petite/utils/database.py
petite/utils/file_system.py
petite_cli-0.1.3.dist-info/LICENSE
petite_cli-0.1.3.dist-info/METADATA
petite_cli-0.1.3.dist-info/WHEEL
petite_cli-0.1.3.dist-info/entry_points.txt
petite_cli-0.1.3.dist-info/RECORD
