Metadata-Version: 2.3
Name: petite-cli
Version: 0.1.3
Summary: A simple PostgreSQL migrations manager
License: MIT
Author: Kyle
Author-email: ky42@protonmail.com
Requires-Python: >=3.10,<4.0
Classifier: Development Status :: 5 - Production/Stable
Classifier: Environment :: Console
Classifier: Intended Audience :: Developers
Classifier: License :: OSI Approved :: MIT License
Classifier: Natural Language :: English
Classifier: Operating System :: OS Independent
Classifier: Programming Language :: Python :: 3
Classifier: Programming Language :: Python :: 3.10
Classifier: Programming Language :: Python :: 3.11
Classifier: Programming Language :: Python :: 3.12
Classifier: Programming Language :: Python :: 3.13
Classifier: Topic :: Database
Classifier: Topic :: Software Development :: Build Tools
Classifier: Typing :: Typed
Requires-Dist: psycopg[binary] (>=3.2.3,<4.0.0)
Requires-Dist: python-dotenv (>=1.0.1,<2.0.0)
Requires-Dist: sqlglot[rs] (>=27.14.0,<28.0.0)
Requires-Dist: typer (>=0.15.0,<0.16.0)
Project-URL: Repository, https://github.com/ky-42/petite
